colarify/__init__.py
colarify/ansi.py
colarify/styled_string.py
colarify/styled_string_builder.py
colarify-1.1.8.dist-info/LICENSE.txt
colarify-1.1.8.dist-info/METADATA
colarify-1.1.8.dist-info/WHEEL
colarify-1.1.8.dist-info/top_level.txt
colarify-1.1.8.dist-info/RECORD
