Metadata-Version: 2.1
Name: colarify
Version: 1.1.8
Summary: Bring life into your project by adding wonderful colors
Home-page: https://github.com/dscklaw/colarify
Author: johndsk
Author-email: smithmark@gmail.com
Classifier: Programming Language :: Python :: 3
Classifier: License :: OSI Approved :: MIT License
Classifier: Operating System :: OS Independent
Requires-Python: >=3.7
License-File: LICENSE.txt
